dictlens/__init__.py
dictlens/core.py
dictlens/py.typed
dictlens-0.1.5.dist-info/licenses/LICENSE
dictlens-0.1.5.dist-info/METADATA
dictlens-0.1.5.dist-info/WHEEL
dictlens-0.1.5.dist-info/top_level.txt
dictlens-0.1.5.dist-info/RECORD
